fastled/__init__.py
fastled/__main__.py
fastled/__version__.py
fastled/app.py
fastled/args.py
fastled/cli.py
fastled/cli_test.py
fastled/cli_test_interactive.py
fastled/client_server.py
fastled/compile_native.py
fastled/compile_server.py
fastled/compile_server_impl.py
fastled/docker_manager.py
fastled/emoji_util.py
fastled/filewatcher.py
fastled/find_good_connection.py
fastled/header_dump.py
fastled/interruptible_http.py
fastled/keyboard.py
fastled/keyz.py
fastled/live_client.py
fastled/open_browser.py
fastled/parse_args.py
fastled/paths.py
fastled/print_filter.py
fastled/project_init.py
fastled/select_sketch_directory.py
fastled/server_flask.py
fastled/server_start.py
fastled/settings.py
fastled/sketch.py
fastled/spinner.py
fastled/string_diff.py
fastled/types.py
fastled/util.py
fastled/version.py
fastled/web_compile.py
fastled/zip_files.py
fastled/assets/example.txt
fastled/assets/localhost-key.pem
fastled/assets/localhost.pem
fastled/install/__init__.py
fastled/install/examples_manager.py
fastled/install/extension_manager.py
fastled/install/main.py
fastled/install/project_detection.py
fastled/install/test_install.py
fastled/install/vscode_config.py
fastled/playwright/chrome_extension_downloader.py
fastled/playwright/playwright_browser.py
fastled/playwright/resize_tracking.py
fastled/site/build.py
fastled/site/examples.py
fastled/test/can_run_local_docker_tests.py
fastled/test/examples.py
fastled/toolchain/__init__.py
fastled/toolchain/emscripten.py
fastled-1.4.54.dist-info/licenses/LICENSE
fastled-1.4.54.dist-info/METADATA
fastled-1.4.54.dist-info/WHEEL
fastled-1.4.54.dist-info/entry_points.txt
fastled-1.4.54.dist-info/top_level.txt
fastled-1.4.54.dist-info/RECORD
