Metadata-Version: 2.4
Name: fastled
Version: 1.4.54
Summary: FastLED Wasm Compiler
Home-page: https://github.com/zackees/fastled-wasm
Maintainer: Zachary Vorhies
License: BSD 3-Clause License
Keywords: template-python-cmd
Classifier: Programming Language :: Python :: 3
Requires-Python: >=3.10
License-File: LICENSE
Requires-Dist: httpx>=0.28.1
Requires-Dist: watchdog>=6.0.0
Requires-Dist: docker>=7.1.0
Requires-Dist: filelock>=3.16.1
Requires-Dist: appdirs>=1.4.4
Requires-Dist: rapidfuzz>=3.10.1
Requires-Dist: progress>=1.6
Requires-Dist: watchfiles>=1.0.5
Requires-Dist: Flask>=3.0.0
Requires-Dist: flask-cors>=4.0.0
Requires-Dist: livereload
Requires-Dist: disklru>=2.0.4
Requires-Dist: playwright>=1.40.0
Requires-Dist: websockify>=0.13.0
Requires-Dist: fasteners>=0.20
Requires-Dist: cryptography>=41.0.0
Dynamic: home-page
Dynamic: license-file
Dynamic: maintainer
